MANIFEST.in
setup.py
autonetkit_vis/__init__.py
autonetkit_vis/notebook.py
autonetkit_vis.egg-info/PKG-INFO
autonetkit_vis.egg-info/SOURCES.txt
autonetkit_vis.egg-info/dependency_links.txt
autonetkit_vis.egg-info/top_level.txt
autonetkit_vis/web_content/3d.html
autonetkit_vis/web_content/FirstPersonControls.js
autonetkit_vis/web_content/OrbitControls.js
autonetkit_vis/web_content/TrackballControls.js
autonetkit_vis/web_content/ank_render.js
autonetkit_vis/web_content/colorbrewer.js
autonetkit_vis/web_content/d3.v3.min.js
autonetkit_vis/web_content/default.css
autonetkit_vis/web_content/default.json.gz
autonetkit_vis/web_content/favicon.ico
autonetkit_vis/web_content/font-awesome.min.css
autonetkit_vis/web_content/helvetiker_regular.typeface.js
autonetkit_vis/web_content/index.html
autonetkit_vis/web_content/ip.html
autonetkit_vis/web_content/jquery-1.7.2.min.js
autonetkit_vis/web_content/jquery.ba-bbq.min.js
autonetkit_vis/web_content/jquery.tipsy.js
autonetkit_vis/web_content/maximised.css
autonetkit_vis/web_content/numeric.json.gz
autonetkit_vis/web_content/print.css
autonetkit_vis/web_content/simple.html
autonetkit_vis/web_content/three.min.js
autonetkit_vis/web_content/tipsy.css
autonetkit_vis/web_content/underscore-min.js
autonetkit_vis/web_content/unsupported_browser.html
autonetkit_vis/web_content/font/FontAwesome.otf
autonetkit_vis/web_content/font/fontawesome-webfont.eot
autonetkit_vis/web_content/font/fontawesome-webfont.ttf
autonetkit_vis/web_content/font/fontawesome-webfont.woff
autonetkit_vis/web_content/icons/ank_internal.svg
autonetkit_vis/web_content/icons/antenna.svg
autonetkit_vis/web_content/icons/broadcast_domain.svg
autonetkit_vis/web_content/icons/external_connector_SNAT.svg
autonetkit_vis/web_content/icons/external_connector_ext_vlan.svg
autonetkit_vis/web_content/icons/null.svg
autonetkit_vis/web_content/icons/router.svg
autonetkit_vis/web_content/icons/router_CSR1000v.svg
autonetkit_vis/web_content/icons/router_IOS XRv.svg
autonetkit_vis/web_content/icons/router_IOSv.svg
autonetkit_vis/web_content/icons/router_NX-OSv.svg
autonetkit_vis/web_content/icons/router_ext_ebgp.svg
