Metadata-Version: 1.0
Name: autonetkit-vis
Version: 0.1.13
Summary: Visualisation for AutoNetkit
Home-page: http://www.autonetkit.org
Author: Simon Knight
Author-email: simon.knight@gmail.com
License: UNKNOWN
Platform: UNKNOWN
